.long-description.html
README.rst
setup.py
src/collective/__init__.py
src/collective.behavior.size.egg-info/PKG-INFO
src/collective.behavior.size.egg-info/SOURCES.txt
src/collective.behavior.size.egg-info/dependency_links.txt
src/collective.behavior.size.egg-info/entry_points.txt
src/collective.behavior.size.egg-info/namespace_packages.txt
src/collective.behavior.size.egg-info/not-zip-safe
src/collective.behavior.size.egg-info/requires.txt
src/collective.behavior.size.egg-info/top_level.txt
src/collective/behavior/__init__.py
src/collective/behavior/size/__init__.py
src/collective/behavior/size/behavior.py
src/collective/behavior/size/configure.zcml
src/collective/behavior/size/interfaces.py
src/collective/behavior/size/schema.py
src/collective/behavior/size/docs/CONTRIBUTORS.rst
src/collective/behavior/size/docs/CREDITS.rst
src/collective/behavior/size/docs/HISTORY.rst
src/collective/behavior/size/docs/INSTALL.rst
src/collective/behavior/size/docs/LICENSE.rst
src/collective/behavior/size/locales/collective.behavior.size.pot
src/collective/behavior/size/locales/fi/LC_MESSAGES/collective.behavior.size.po
src/collective/behavior/size/profiles/default/metadata.xml
src/collective/behavior/size/tests/__init__.py
src/collective/behavior/size/tests/base.py
src/collective/behavior/size/tests/test_ISize.py
src/collective/behavior/size/tests/test_Size.py
src/collective/behavior/size/tests/test_setup.py